keskivonfer/__init__.py
keskivonfer/core.py
keskivonfer-1.1.dist-info/METADATA
keskivonfer-1.1.dist-info/WHEEL
keskivonfer-1.1.dist-info/top_level.txt
keskivonfer-1.1.dist-info/RECORD
