Metadata-Version: 2.1
Name: keskivonfer
Version: 1.1
Summary: Keskivonfer is a tool that allows you to extract information from a vinted account
Home-page: http://github.com/megadose/keskivonfer
Author: megadose
Author-email: UNKNOWN
License: UNKNOWN
Platform: UNKNOWN
Classifier: Programming Language :: Python
Classifier: License :: OSI Approved :: GNU General Public License v3 (GPLv3)
Requires-Dist: argparse
Requires-Dist: fake-useragent
